README.md
setup.py
electiondata/__init__.py
electiondata/aggregator.py
electiondata/alaska.py
electiondata/clean.py
electiondata/data_source.py
electiondata/download.py
electiondata/errors.py
electiondata/matcher.py
electiondata/merge.py
electiondata/name_normalizer.py
electiondata/party_normalizer.py
electiondata/rewrite.py
electiondata/uncontested.py
electiondata/utils.py
electiondata/validate.py
electiondata.egg-info/PKG-INFO
electiondata.egg-info/SOURCES.txt
electiondata.egg-info/dependency_links.txt
electiondata.egg-info/requires.txt
electiondata.egg-info/top_level.txt
electiondata/examples/__init__.py
electiondata/examples/canonical_2018_general.py
electiondata/examples/census_2010_pop.py
electiondata/examples/census_apportionment.py
electiondata/examples/harvard_dataverse_2018_general.py
electiondata/examples/harvard_dataverse_congress_district_results.py
electiondata/examples/mit_election_lab_2018_general.py
electiondata/examples/nytimes_num_colleges.py
electiondata/examples/plotly_geojson.py